gaudit/__init__.py
gaudit/__main__.py
gaudit/cli.py
gaudit/client.py
gaudit/config.py
gaudit/elfbuilder.py
gaudit/ida/__init__.py
gaudit/ida/idbtoelf.py
gaudit/ida/plugin.py
gaudit/ida/ui.py
gaudit/ida/version.py
gaudit-0.3.1.dist-info/licenses/LICENSE
gaudit-0.3.1.dist-info/METADATA
gaudit-0.3.1.dist-info/WHEEL
gaudit-0.3.1.dist-info/entry_points.txt
gaudit-0.3.1.dist-info/top_level.txt
gaudit-0.3.1.dist-info/RECORD
