Metadata-Version: 2.4
Name: gaudit
Version: 0.3.1
Summary: Library and CLI for GLIMPS Audit API
Author-email: GLIMPS dev core team <contact@glimps.re>
Keywords: python,glimps,reverse engineering,malware,binary,analysis,ida
Classifier: Development Status :: 5 - Production/Stable
Classifier: Programming Language :: Python :: 3
Classifier: Operating System :: MacOS :: MacOS X
Classifier: Operating System :: Microsoft :: Windows
Classifier: Operating System :: POSIX :: Linux
Classifier: License :: OSI Approved :: MIT License
Classifier: Programming Language :: Python :: 3.8
Classifier: Programming Language :: Python :: 3.9
Classifier: Programming Language :: Python :: 3.10
Classifier: Programming Language :: Python :: 3.11
Classifier: Programming Language :: Python :: 3.12
Classifier: Programming Language :: Python :: 3.13
Requires-Python: >=3.8
License-File: LICENSE
Requires-Dist: click~=8.0
Requires-Dist: click-default-group~=1.2
Requires-Dist: requests~=2.32
Requires-Dist: rich~=11.0
Requires-Dist: construct~=2.10
Dynamic: license-file
